xmlfuse/__init__.py
xmlfuse/fuse.py
xmlfuse-0.0.4.dist-info/LICENSE
xmlfuse-0.0.4.dist-info/METADATA
xmlfuse-0.0.4.dist-info/WHEEL
xmlfuse-0.0.4.dist-info/top_level.txt
xmlfuse-0.0.4.dist-info/RECORD
